src/ladder/__init__.py
src/ladder/widgets.py
layouttkinter-0.1.1.dist-info/WHEEL
layouttkinter-0.1.1.dist-info/METADATA
layouttkinter-0.1.1.dist-info/RECORD
